colibricf/__init__.py
colibricf/camera.py
colibricf/drone.py
colibricf/servo.py
colibricf/task.py
colibricf/apps/__init__.py
colibricf/apps/follow.py
colibricf/apps/gesture_control.py
colibricf/apps/handlers/follow.py
colibricf/apps/handlers/gesture_control.py
colibricf/camera_utils/recorder.py
colibricf/camera_utils/topic_rate.py
colibricf/cv/__init__.py
colibricf/cv/utils.py
colibricf/files/filemanager.py
colibricf/files/logger.py
colibricf-1.1.8.dist-info/LICENSE
colibricf-1.1.8.dist-info/METADATA
colibricf-1.1.8.dist-info/WHEEL
colibricf-1.1.8.dist-info/top_level.txt
colibricf-1.1.8.dist-info/RECORD
