Metadata-Version: 2.1
Name: colibricf
Version: 1.1.8
Summary: Code functions to control a Drone using clover
Author-email: Educa Drones <educadrones.contato@gmail.com>, Bruno Rodrigues <brunorodriguesmtv0@gmail.com>, Gabriel Montalvão <gabriel.msantos7@hotmail.com>
License: MIT
Project-URL: Homepage, https://github.com/EDUCA-DRONES/Colibri_CF
Project-URL: Repository, https://github.com/EDUCA-DRONES/Colibri_CF
Requires-Python: >=3.7
License-File: LICENSE
